{
  "info": {
    "name": "Travel Buddy – User Service (TV1)",
    "description": "Postman collection for User Service (:8081). JWT payload: { userId, email, iat, exp }",
    "schema": "https://schema.getpostman.com/json/collection/v2.1.0/collection.json"
  },
  "variable": [
    { "key": "baseUrl", "value": "http://localhost:8081" },
    { "key": "token",   "value": "" }
  ],
  "item": [
    {
      "name": "Auth",
      "item": [
        {
          "name": "Register",
          "request": {
            "method": "POST",
            "header": [{ "key": "Content-Type", "value": "application/json" }],
            "url": { "raw": "{{baseUrl}}/auth/register", "host": ["{{baseUrl}}"], "path": ["auth","register"] },
            "body": {
              "mode": "raw",
              "raw": "{\n  \"name\": \"Nguyen Van A\",\n  \"email\": \"nguyenvana@example.com\",\n  \"password\": \"secret123\",\n  \"bio\": \"Thích đi phượt\",\n  \"tags\": [\"backpacker\", \"budget-travel\"]\n}"
            }
          },
          "event": [
            {
              "listen": "test",
              "script": {
                "exec": [
                  "pm.test('Status 201', () => pm.response.to.have.status(201));",
                  "pm.test('Has id', () => pm.expect(pm.response.json().id).to.be.a('string'));",
                  "pm.test('Has createdAt', () => pm.expect(pm.response.json().createdAt).to.be.a('string'));"
                ]
              }
            }
          ]
        },
        {
          "name": "Register – Email Duplicate (expect 400)",
          "request": {
            "method": "POST",
            "header": [{ "key": "Content-Type", "value": "application/json" }],
            "url": { "raw": "{{baseUrl}}/auth/register", "host": ["{{baseUrl}}"], "path": ["auth","register"] },
            "body": {
              "mode": "raw",
              "raw": "{\n  \"name\": \"Nguyen Van A\",\n  \"email\": \"nguyenvana@example.com\",\n  \"password\": \"secret123\"\n}"
            }
          },
          "event": [
            {
              "listen": "test",
              "script": {
                "exec": [
                  "pm.test('Status 400', () => pm.response.to.have.status(400));",
                  "pm.test('Error EMAIL_ALREADY_EXISTS', () => pm.expect(pm.response.json().error).to.eql('EMAIL_ALREADY_EXISTS'));"
                ]
              }
            }
          ]
        },
        {
          "name": "Login",
          "request": {
            "method": "POST",
            "header": [{ "key": "Content-Type", "value": "application/json" }],
            "url": { "raw": "{{baseUrl}}/auth/login", "host": ["{{baseUrl}}"], "path": ["auth","login"] },
            "body": {
              "mode": "raw",
              "raw": "{\n  \"email\": \"nguyenvana@example.com\",\n  \"password\": \"secret123\"\n}"
            }
          },
          "event": [
            {
              "listen": "test",
              "script": {
                "exec": [
                  "pm.test('Status 200', () => pm.response.to.have.status(200));",
                  "const body = pm.response.json();",
                  "pm.test('Has accessToken', () => pm.expect(body.accessToken).to.be.a('string'));",
                  "pm.test('Has user.id', () => pm.expect(body.user.id).to.be.a('string'));",
                  "pm.collectionVariables.set('token', body.accessToken);",
                  "// Verify JWT payload có userId và email (decode base64 middle part)",
                  "const parts = body.accessToken.split('.');",
                  "const payload = JSON.parse(atob(parts[1]));",
                  "pm.test('JWT payload has userId', () => pm.expect(payload.userId).to.be.a('string'));",
                  "pm.test('JWT payload has email', () => pm.expect(payload.email).to.be.a('string'));"
                ]
              }
            }
          ]
        },
        {
          "name": "Login – Wrong Password (expect 401)",
          "request": {
            "method": "POST",
            "header": [{ "key": "Content-Type", "value": "application/json" }],
            "url": { "raw": "{{baseUrl}}/auth/login", "host": ["{{baseUrl}}"], "path": ["auth","login"] },
            "body": {
              "mode": "raw",
              "raw": "{\n  \"email\": \"nguyenvana@example.com\",\n  \"password\": \"wrongpassword\"\n}"
            }
          },
          "event": [
            {
              "listen": "test",
              "script": {
                "exec": [
                  "pm.test('Status 401', () => pm.response.to.have.status(401));",
                  "pm.test('Error INVALID_CREDENTIALS', () => pm.expect(pm.response.json().error).to.eql('INVALID_CREDENTIALS'));"
                ]
              }
            }
          ]
        }
      ]
    },
    {
      "name": "Users",
      "item": [
        {
          "name": "Get User by ID",
          "request": {
            "method": "GET",
            "header": [
              { "key": "Authorization", "value": "Bearer {{token}}" }
            ],
            "url": {
              "raw": "{{baseUrl}}/users/{{userId}}",
              "host": ["{{baseUrl}}"],
              "path": ["users","{{userId}}"],
              "variable": [{ "key": "userId", "value": "PASTE_UUID_HERE" }]
            }
          },
          "event": [
            {
              "listen": "test",
              "script": {
                "exec": [
                  "pm.test('Status 200', () => pm.response.to.have.status(200));",
                  "const body = pm.response.json();",
                  "pm.test('Has id', () => pm.expect(body.id).to.be.a('string'));",
                  "pm.test('Has email', () => pm.expect(body.email).to.be.a('string'));",
                  "pm.test('No password field', () => pm.expect(body.password).to.be.undefined);"
                ]
              }
            }
          ]
        },
        {
          "name": "Get User – No Token (expect 401)",
          "request": {
            "method": "GET",
            "header": [],
            "url": {
              "raw": "{{baseUrl}}/users/00000000-0000-0000-0000-000000000000",
              "host": ["{{baseUrl}}"],
              "path": ["users","00000000-0000-0000-0000-000000000000"]
            }
          },
          "event": [
            {
              "listen": "test",
              "script": {
                "exec": [
                  "pm.test('Status 401 or 403', () => pm.expect([401,403]).to.include(pm.response.code));"
                ]
              }
            }
          ]
        },
        {
          "name": "Get User – Not Found (expect 404)",
          "request": {
            "method": "GET",
            "header": [
              { "key": "Authorization", "value": "Bearer {{token}}" }
            ],
            "url": {
              "raw": "{{baseUrl}}/users/00000000-0000-0000-0000-000000000000",
              "host": ["{{baseUrl}}"],
              "path": ["users","00000000-0000-0000-0000-000000000000"]
            }
          },
          "event": [
            {
              "listen": "test",
              "script": {
                "exec": [
                  "pm.test('Status 404', () => pm.response.to.have.status(404));",
                  "pm.test('Error USER_NOT_FOUND', () => pm.expect(pm.response.json().error).to.eql('USER_NOT_FOUND'));"
                ]
              }
            }
          ]
        }
      ]
    }
  ]
}
